opentelemetry/instrumentation/watsonx/__init__.py
opentelemetry/instrumentation/watsonx/config.py
opentelemetry/instrumentation/watsonx/event_emitter.py
opentelemetry/instrumentation/watsonx/event_models.py
opentelemetry/instrumentation/watsonx/utils.py
opentelemetry/instrumentation/watsonx/version.py
opentelemetry_instrumentation_watsonx-0.51.1.dist-info/METADATA
opentelemetry_instrumentation_watsonx-0.51.1.dist-info/WHEEL
opentelemetry_instrumentation_watsonx-0.51.1.dist-info/entry_points.txt
opentelemetry_instrumentation_watsonx-0.51.1.dist-info/RECORD
